Metadata-Version: 2.1
Name: aiojikan
Version: 0.0.1
Summary: A up to date asynchronous api wrapper for the jikan api
Home-page: http://github.com/Leg3ndary/aiojikan
Author: Ben Zhou
Author-email: bleg3ndary@gmail.com
License: MIT
Keywords: api jikan wrapper
Platform: UNKNOWN
Classifier: Development Status :: 1 - Planning
Classifier: Framework :: aiohttp
Classifier: Intended Audience :: Developers
Classifier: License :: OSI Approved :: MIT License
Classifier: Programming Language :: Python :: 3.9
Classifier: Topic :: Utilities
License-File: LICENSE
